testing_pypi_sic/__init__.py
testing_pypi_sic/factorial.py
testing_pypi_sic-0.0.1.dist-info/METADATA
testing_pypi_sic-0.0.1.dist-info/WHEEL
testing_pypi_sic-0.0.1.dist-info/top_level.txt
testing_pypi_sic-0.0.1.dist-info/RECORD
