Metadata-Version: 2.1
Name: testing-pypi-sic
Version: 0.0.1
Summary: Demo sic club activities
Author-email: Putu Widyantara <putuwaw973@gmail.com>
Project-URL: Homepage, https://github.com/putuwaw/testing-pypi-sic
Classifier: Programming Language :: Python :: 3
Classifier: License :: OSI Approved :: MIT License
Classifier: Operating System :: OS Independent
Requires-Python: >=3.8
